buct_pdf/__init__.py
buct_pdf/cli.py
buct_pdf/core.py
buct_pdf-0.5.0.dist-info/METADATA
buct_pdf-0.5.0.dist-info/WHEEL
buct_pdf-0.5.0.dist-info/entry_points.txt
buct_pdf-0.5.0.dist-info/top_level.txt
buct_pdf-0.5.0.dist-info/RECORD
