Metadata-Version: 2.4
Name: buct-pdf
Version: 0.5.0
Summary: 北京化工大学课程平台PDF下载工具，支持登录、下载PPT和PDF文件
Author-email: Your Name <your.email@example.com>
Project-URL: Homepage, https://github.com/your-username/buct-pdf
Project-URL: Repository, https://github.com/your-username/buct-pdf
Project-URL: Bug Tracker, https://github.com/your-username/buct-pdf/issues
Keywords: buct,pdf,download,education
Classifier: Development Status :: 3 - Alpha
Classifier: Intended Audience :: Education
Classifier: License :: OSI Approved :: MIT License
Classifier: Programming Language :: Python :: 3
Classifier: Programming Language :: Python :: 3.12
Requires-Python: >=3.12
Requires-Dist: beautifulsoup4>=4.14.3
Requires-Dist: pillow>=12.0.0
Requires-Dist: requests>=2.32.5
